st_microservice/__init__.py
st_microservice/auth_utils.py
st_microservice/backend_connector.py
st_microservice/base.graphql
st_microservice/database.py
st_microservice/exceptions.py
st_microservice/filter_parser.py
st_microservice/general_utils.py
st_microservice/graphql_app.py
st_microservice/graphql_utils.py
st_microservice/models_utils.py
st_microservice/querybuilder.py
st_microservice/request_utils.py
st_microservice/starlette_backend.py
st_microservice/background_tasks/__init__.py
st_microservice/background_tasks/queue.py
st_microservice/background_tasks/worker_utils.py
st_microservice/models_functions/__init__.py
st_microservice/models_functions/functions.py
st_microservice-2.5.5.dist-info/METADATA
st_microservice-2.5.5.dist-info/WHEEL
st_microservice-2.5.5.dist-info/licenses/LICENSE.txt
st_microservice-2.5.5.dist-info/RECORD
